README.md
setup.py
stegoveritas/Colorer.py
stegoveritas/__init__.py
stegoveritas/helpers.py
stegoveritas/hide_lsb.py
stegoveritas/stegoveritas.py
stegoveritas/version.py
stegoveritas.egg-info/PKG-INFO
stegoveritas.egg-info/SOURCES.txt
stegoveritas.egg-info/dependency_links.txt
stegoveritas.egg-info/entry_points.txt
stegoveritas.egg-info/requires.txt
stegoveritas.egg-info/top_level.txt
stegoveritas/modules/__init__.py
stegoveritas/modules/image/__init__.py
stegoveritas/modules/image/gif.py
stegoveritas/modules/image/png.py
stegoveritas/modules/image/analysis/__init__.py
stegoveritas/modules/image/analysis/brute_lsb.py
stegoveritas/modules/image/analysis/colormap.py
stegoveritas/modules/image/analysis/extractLSB.py
stegoveritas/modules/image/analysis/extract_frames.py
stegoveritas/modules/image/analysis/filters.py
stegoveritas/modules/image/analysis/meta.py
stegoveritas/modules/image/analysis/steghide.py
stegoveritas/modules/image/analysis/trailing.py
stegoveritas/modules/multi/__init__.py
stegoveritas/modules/multi/analysis/__init__.py
stegoveritas/modules/multi/analysis/carve.py
stegoveritas/modules/multi/analysis/exif.py
stegoveritas/modules/multi/analysis/xmp.py
stegoveritas_install_deps/Colorer.py
stegoveritas_install_deps/__init__.py
stegoveritas_install_deps/install_deps.py