Metadata-Version: 2.1
Name: stegoveritas
Version: 1.9
Summary: General Steganography detection tool.
Home-page: https://github.com/bannsec/stegoVeritas
Author: Michael Bann
Author-email: self@bannsecurity.com
License: MIT
Keywords: steg stego steganography stegoveritas
Platform: UNKNOWN
Classifier: Development Status :: 3 - Alpha
Classifier: Intended Audience :: End Users/Desktop
Classifier: License :: OSI Approved :: MIT License
Classifier: Programming Language :: Python :: 3
Classifier: Operating System :: POSIX :: Linux
Classifier: Environment :: Console
Provides-Extra: dev
